MANIFEST.in
README.md
requirements.txt
setup.cfg
setup.py
elastic_funnel/__init__.py
elastic_funnel/cli.py
elastic_funnel/elasticsearch_data.py
elastic_funnel/funnel.py
elastic_funnel/funnel_web.py
elastic_funnel.egg-info/PKG-INFO
elastic_funnel.egg-info/SOURCES.txt
elastic_funnel.egg-info/dependency_links.txt
elastic_funnel.egg-info/entry_points.txt
elastic_funnel.egg-info/requires.txt
elastic_funnel.egg-info/top_level.txt