Metadata-Version: 1.1
Name: elastic-funnel
Version: 0.1.6
Summary: Analysis tool for funnel visualization with log from Elasticsearch
Home-page: https://github.com/yuecen/elastic_funnel
Author: yuecen
Author-email: yuecendev+pypi@gmail.com
License: MIT
Keywords: elasticsearch,log,funnel,elastic_funnel
Platform: UNKNOWN
Classifier: Intended Audience :: Developers
Classifier: Programming Language :: Python
